dtrg_specified/__init__.py
keyvault/__init__.py
azure_integration-0.0.4.dist-info/METADATA
azure_integration-0.0.4.dist-info/WHEEL
azure_integration-0.0.4.dist-info/top_level.txt
azure_integration-0.0.4.dist-info/RECORD
