Metadata-Version: 2.1
Name: azure-integration
Version: 0.0.4
Summary: Microsoft Azure Integration
Home-page: https://github.com/IOMehran/azure-integration
Author: Mehran Zolghadr
Author-email: mehran@keyleadhealth.com
License: UNKNOWN
Download-URL: https://github.com/IOMehran/azure-integration/archive/refs/tags/v0.0.3.tar.gz
Project-URL: Bug Tracker, https://github.com/IOMehran/azure-integration/issues
Platform: UNKNOWN
Classifier: Programming Language :: Python :: 3
Classifier: License :: OSI Approved :: MIT License
Classifier: Operating System :: OS Independent
Requires-Python: >=3.6
Requires-Dist: azure-common (==1.1.27)
Requires-Dist: azure-core (==1.13.0)
Requires-Dist: azure-identity (==1.5.0)
Requires-Dist: azure-keyvault (==4.1.0)
Requires-Dist: azure-keyvault-certificates (==4.2.1)
Requires-Dist: azure-keyvault-keys (==4.3.1)
Requires-Dist: azure-keyvault-secrets (==4.2.0)
Requires-Dist: build (==0.3.1.post1)
Requires-Dist: certifi (==2020.12.5)
Requires-Dist: cffi (==1.14.5)
Requires-Dist: chardet (==4.0.0)
Requires-Dist: cryptography (==3.4.7)
Requires-Dist: idna (==2.10)
Requires-Dist: isodate (==0.6.0)
Requires-Dist: msal (==1.11.0)
Requires-Dist: msal-extensions (==0.3.0)
Requires-Dist: msrest (==0.6.21)
Requires-Dist: oauthlib (==3.1.0)
Requires-Dist: packaging (==20.9)
Requires-Dist: pep517 (==0.10.0)
Requires-Dist: portalocker (==1.7.1)
Requires-Dist: pycparser (==2.20)
Requires-Dist: PyJWT (==2.0.1)
Requires-Dist: pyparsing (==2.4.7)
Requires-Dist: python-dotenv (==0.17.0)
Requires-Dist: requests (==2.25.1)
Requires-Dist: requests-oauthlib (==1.3.0)
Requires-Dist: six (==1.15.0)
Requires-Dist: toml (==0.10.2)
Requires-Dist: urllib3 (==1.26.4)
Requires-Dist: gobject
